README
setup.py
django_key.egg-info/PKG-INFO
django_key.egg-info/SOURCES.txt
django_key.egg-info/dependency_links.txt
django_key.egg-info/requires.txt
django_key.egg-info/top_level.txt
key/__init__.py
key/auth.py
key/forms.py
key/settings.py
key/signals.py
key/urls.py
key/views.py
key/admin/__init__.py
key/admin/admin.py
key/admin/forms.py
key/migrations/0001_initial.py
key/migrations/0002_auto__add_field_apikeyprofile_last_access.py
key/migrations/0003_auto__chg_field_apikey_logged_ip.py
key/migrations/0004_auto__chg_field_apikey_key.py
key/migrations/0005_auto__del_apikey__del_apikeyprofile.py
key/migrations/0006_auto__add_apikey__add_apikeyprofile.py
key/migrations/__init__.py
key/models/__init__.py
key/models/actions.py
key/models/models.py
key/tests/__init__.py
key/tests/test_key.py
key/tests/test_urls.py