Metadata-Version: 1.0
Name: django-key
Version: 0.5.0
Summary: Simple, straight forward API key for django-piston.
Home-page: https://github.com/scoursen/django-apikey
Author: Steve Coursen
Author-email: smcoursen@gmail.com
License: BSD
Platform: UNKNOWN
